MANIFEST.in
README.md
setup.py
jen/__init__.py
jen/build.py
jen/cli.py
jen/main.py
jen/run.py
jen/template_renderer.py
jen.egg-info/PKG-INFO
jen.egg-info/SOURCES.txt
jen.egg-info/dependency_links.txt
jen.egg-info/entry_points.txt
jen.egg-info/requires.txt
jen.egg-info/top_level.txt