Metadata-Version: 1.0
Name: jen
Version: 0.0.0
Summary: Static site generator and prototyping tool based on Jinja2.
Home-page: https://github.com/hugollm/jen
Author: Hugo Leonardo Leão Mota
Author-email: hugo.txt@gmail.com
License: MIT
Keywords: jen static site generator prototype build
Platform: UNKNOWN
